opencv_helper/__init__.py
opencv_helper/capcity.py
opencv_helper/cv.py
opencv_helper/utils.py
opencv_helper-2.0.0.dist-info/METADATA
opencv_helper-2.0.0.dist-info/WHEEL
opencv_helper-2.0.0.dist-info/top_level.txt
opencv_helper-2.0.0.dist-info/RECORD
