Metadata-Version: 2.1
Name: opencv_helper
Version: 2.0.0
Summary: opencv helper
Home-page: 
Author: guozi
Author-email: 421826878@qq.com
License: MIT
Classifier: License :: OSI Approved :: MIT License
Classifier: Programming Language :: Python
Classifier: Programming Language :: Python :: 3
Classifier: Programming Language :: Python :: 3.6
Classifier: Programming Language :: Python :: Implementation :: CPython
Classifier: Programming Language :: Python :: Implementation :: PyPy
Requires-Python: >=3.6.0
Requires-Dist: opencv-python
Requires-Dist: numpy
Requires-Dist: mss
Requires-Dist: pywin32
